{
  "resolvedId": "C:/Users/DT User/Desktop/ProjektPZI/frontend/node_modules/vuetify/lib/components/VCard/VCardItem.mjs",
  "transforms": [
    {
      "name": "vite:load-fallback",
      "result": "import { resolveDirective as _resolveDirective, createVNode as _createVNode } from \"vue\";\n// Components\nimport { VCardSubtitle } from \"./VCardSubtitle.mjs\";\nimport { VCardTitle } from \"./VCardTitle.mjs\";\nimport { VAvatar } from \"../VAvatar/index.mjs\";\nimport { VDefaultsProvider } from \"../VDefaultsProvider/index.mjs\"; // Composables\nimport { makeComponentProps } from \"../../composables/component.mjs\";\nimport { makeDensityProps } from \"../../composables/density.mjs\";\nimport { IconValue } from \"../../composables/icons.mjs\"; // Utilities\nimport { genericComponent, propsFactory, useRender } from \"../../util/index.mjs\";\nexport const makeCardItemProps = propsFactory({\n  appendAvatar: String,\n  appendIcon: IconValue,\n  prependAvatar: String,\n  prependIcon: IconValue,\n  subtitle: [String, Number],\n  title: [String, Number],\n  ...makeComponentProps(),\n  ...makeDensityProps()\n}, 'VCardItem');\nexport const VCardItem = genericComponent()({\n  name: 'VCardItem',\n  props: makeCardItemProps(),\n  setup(props, _ref) {\n    let {\n      slots\n    } = _ref;\n    useRender(() => {\n      const hasPrependMedia = !!(props.prependAvatar || props.prependIcon);\n      const hasPrepend = !!(hasPrependMedia || slots.prepend);\n      const hasAppendMedia = !!(props.appendAvatar || props.appendIcon);\n      const hasAppend = !!(hasAppendMedia || slots.append);\n      const hasTitle = !!(props.title != null || slots.title);\n      const hasSubtitle = !!(props.subtitle != null || slots.subtitle);\n      return _createVNode(\"div\", {\n        \"class\": ['v-card-item', props.class],\n        \"style\": props.style\n      }, [hasPrepend && _createVNode(\"div\", {\n        \"key\": \"prepend\",\n        \"class\": \"v-card-item__prepend\"\n      }, [!slots.prepend ? hasPrependMedia && _createVNode(VAvatar, {\n        \"key\": \"prepend-avatar\",\n        \"density\": props.density,\n        \"icon\": props.prependIcon,\n        \"image\": props.prependAvatar\n      }, null) : _createVNode(VDefaultsProvider, {\n        \"key\": \"prepend-defaults\",\n        \"disabled\": !hasPrependMedia,\n        \"defaults\": {\n          VAvatar: {\n            density: props.density,\n            icon: props.prependIcon,\n            image: props.prependAvatar\n          }\n        }\n      }, slots.prepend)]), _createVNode(\"div\", {\n        \"class\": \"v-card-item__content\"\n      }, [hasTitle && _createVNode(VCardTitle, {\n        \"key\": \"title\"\n      }, {\n        default: () => [slots.title?.() ?? props.title]\n      }), hasSubtitle && _createVNode(VCardSubtitle, {\n        \"key\": \"subtitle\"\n      }, {\n        default: () => [slots.subtitle?.() ?? props.subtitle]\n      }), slots.default?.()]), hasAppend && _createVNode(\"div\", {\n        \"key\": \"append\",\n        \"class\": \"v-card-item__append\"\n      }, [!slots.append ? hasAppendMedia && _createVNode(VAvatar, {\n        \"key\": \"append-avatar\",\n        \"density\": props.density,\n        \"icon\": props.appendIcon,\n        \"image\": props.appendAvatar\n      }, null) : _createVNode(VDefaultsProvider, {\n        \"key\": \"append-defaults\",\n        \"disabled\": !hasAppendMedia,\n        \"defaults\": {\n          VAvatar: {\n            density: props.density,\n            icon: props.appendIcon,\n            image: props.appendAvatar\n          }\n        }\n      }, slots.append)])]);\n    });\n    return {};\n  }\n});\n//# sourceMappingURL=VCardItem.mjs.map",
      "start": 1721076617640,
      "end": 1721076617789,
      "sourcemaps": null
    },
    {
      "name": "nuxt:layer-aliasing",
      "start": 1721076617789,
      "end": 1721076617789,
      "order": "pre"
    },
    {
      "name": "nuxt:server-devonly:transform",
      "start": 1721076617789,
      "end": 1721076617789,
      "order": "pre"
    },
    {
      "name": "nuxt:client-fallback-auto-id",
      "start": 1721076617789,
      "end": 1721076617789,
      "order": "pre"
    },
    {
      "name": "vite:css",
      "start": 1721076617789,
      "end": 1721076617789,
      "order": "normal"
    },
    {
      "name": "vite:esbuild",
      "start": 1721076617789,
      "end": 1721076617789,
      "order": "normal"
    },
    {
      "name": "vite:json",
      "start": 1721076617789,
      "end": 1721076617789,
      "order": "normal"
    },
    {
      "name": "vite:worker",
      "start": 1721076617789,
      "end": 1721076617789,
      "order": "normal"
    },
    {
      "name": "vite:vue",
      "start": 1721076617789,
      "end": 1721076617789,
      "order": "normal"
    },
    {
      "name": "vite:vue-jsx",
      "start": 1721076617789,
      "end": 1721076617789,
      "order": "normal"
    },
    {
      "name": "replace",
      "start": 1721076617789,
      "end": 1721076617789,
      "order": "normal"
    },
    {
      "name": "nuxt:remove-plugin-metadata",
      "start": 1721076617789,
      "end": 1721076617789,
      "order": "normal"
    },
    {
      "name": "nuxt:chunk-error",
      "start": 1721076617789,
      "end": 1721076617789,
      "order": "normal"
    },
    {
      "name": "vuetify:import",
      "start": 1721076617789,
      "end": 1721076617789,
      "order": "normal"
    },
    {
      "name": "nuxt:components:imports",
      "start": 1721076617789,
      "end": 1721076617790,
      "order": "normal"
    },
    {
      "name": "replace",
      "start": 1721076617790,
      "end": 1721076617790,
      "order": "normal"
    },
    {
      "name": "ssr-styles",
      "start": 1721076617790,
      "end": 1721076617790,
      "order": "normal"
    },
    {
      "name": "vite:define",
      "start": 1721076617790,
      "end": 1721076617790,
      "order": "normal"
    },
    {
      "name": "vite:css-post",
      "start": 1721076617790,
      "end": 1721076617790,
      "order": "normal"
    },
    {
      "name": "vite:build-html",
      "start": 1721076617790,
      "end": 1721076617790,
      "order": "normal"
    },
    {
      "name": "vite:worker-import-meta-url",
      "start": 1721076617790,
      "end": 1721076617790,
      "order": "normal"
    },
    {
      "name": "vite:asset-import-meta-url",
      "start": 1721076617790,
      "end": 1721076617790,
      "order": "normal"
    },
    {
      "name": "commonjs",
      "start": 1721076617790,
      "end": 1721076617790,
      "order": "normal"
    },
    {
      "name": "vite:dynamic-import-vars",
      "start": 1721076617790,
      "end": 1721076617790,
      "order": "normal"
    },
    {
      "name": "vite:import-glob",
      "start": 1721076617790,
      "end": 1721076617790,
      "order": "normal"
    },
    {
      "name": "nuxt:composable-keys",
      "start": 1721076617790,
      "end": 1721076617790,
      "order": "post"
    },
    {
      "name": "nuxt:imports-transform",
      "start": 1721076617790,
      "end": 1721076617790,
      "order": "post"
    },
    {
      "name": "unctx:transform",
      "start": 1721076617790,
      "end": 1721076617790,
      "order": "post"
    },
    {
      "name": "nuxt:pages-macros-transform",
      "start": 1721076617790,
      "end": 1721076617790,
      "order": "post"
    },
    {
      "name": "nuxt:runtime-paths-dep",
      "start": 1721076617790,
      "end": 1721076617790,
      "order": "post"
    },
    {
      "name": "nuxt:route-injection-plugin",
      "start": 1721076617790,
      "end": 1721076617790,
      "order": "post"
    },
    {
      "name": "nuxt:components-loader",
      "start": 1721076617790,
      "end": 1721076617790,
      "order": "post"
    },
    {
      "name": "nuxt:tree-shake-composables:transform",
      "start": 1721076617790,
      "end": 1721076617790,
      "order": "post"
    },
    {
      "name": "vite:build-import-analysis",
      "start": 1721076617790,
      "end": 1721076617790,
      "order": "normal"
    },
    {
      "name": "vite:reporter",
      "start": 1721076617790,
      "end": 1721076617790,
      "order": "normal"
    }
  ]
}
